MANIFEST.in
readme.md
requirements.txt
setup.py
src/eduard_first_project/__init__.py
src/eduard_first_project.egg-info/PKG-INFO
src/eduard_first_project.egg-info/SOURCES.txt
src/eduard_first_project.egg-info/dependency_links.txt
src/eduard_first_project.egg-info/requires.txt
src/eduard_first_project.egg-info/top_level.txt