Metadata-Version: 2.1
Name: eduard-first-project
Version: 0.1.0
Summary: Says Hello
Author: Eduard Gabriel Lupascu
Author-email: eduardglupascu@gmail.com
License: UNKNOWN
Platform: UNKNOWN
